PyValidationTool/__init__.py
PyValidationTool/replaceSensitiveWords.py
PyValidationTool/sensitiveWords.py
PyValidationTool/validator.py
PyValidationTool-0.1.9.dist-info/LICENSE
PyValidationTool-0.1.9.dist-info/METADATA
PyValidationTool-0.1.9.dist-info/WHEEL
PyValidationTool-0.1.9.dist-info/top_level.txt
PyValidationTool-0.1.9.dist-info/zip-safe
PyValidationTool-0.1.9.dist-info/RECORD
