Metadata-Version: 2.1
Name: PyValidationTool
Version: 0.1.9
Summary: Common validation method in China.
Home-page: https://github.com/Wuliaodewo/PyValidationTool
Author: Simon_He
Author-email: simonheusing@gmail.com
Maintainer: Simon_He
Maintainer-email: simonheusing@gmail.com
License: MIT
Keywords: common validation tool 身份证手机号码中文名字验证类
Platform: UNKNOWN
